IQtools/CLI.py
IQtools/IQdata.py
IQtools/SignalAnalyzer.py
IQtools/SignalGenerator.py
IQtools/__init__.py
iqtools-0.7.3.dist-info/LICENSE
iqtools-0.7.3.dist-info/METADATA
iqtools-0.7.3.dist-info/WHEEL
iqtools-0.7.3.dist-info/entry_points.txt
iqtools-0.7.3.dist-info/RECORD
